[
  {
    "idx": 1,
    "face": null,
    "start_line_idx": 2,
    "end_line_idx": 5,
    "num_content_lines": 2
  },
  {
    "idx": 2,
    "face": null,
    "start_line_idx": 8,
    "end_line_idx": 10,
    "num_content_lines": 1
  },
  {
    "idx": 3,
    "face": null,
    "start_line_idx": 19,
    "end_line_idx": 21,
    "num_content_lines": 1
  },
  {
    "idx": 4,
    "face": null,
    "start_line_idx": 24,
    "end_line_idx": 26,
    "num_content_lines": 1
  },
  {
    "idx": 5,
    "face": null,
    "start_line_idx": 29,
    "end_line_idx": 32,
    "num_content_lines": 2
  },
  {
    "idx": 6,
    "face": null,
    "start_line_idx": 35,
    "end_line_idx": 37,
    "num_content_lines": 1
  },
  {
    "idx": 7,
    "face": null,
    "start_line_idx": 44,
    "end_line_idx": 47,
    "num_content_lines": 2
  },
  {
    "idx": 8,
    "face": null,
    "start_line_idx": 50,
    "end_line_idx": 52,
    "num_content_lines": 1
  },
  {
    "idx": 9,
    "face": null,
    "start_line_idx": 61,
    "end_line_idx": 63,
    "num_content_lines": 1
  },
  {
    "idx": 10,
    "face": null,
    "start_line_idx": 66,
    "end_line_idx": 68,
    "num_content_lines": 1
  },
  {
    "idx": 11,
    "face": null,
    "start_line_idx": 71,
    "end_line_idx": 74,
    "num_content_lines": 2
  },
  {
    "idx": 12,
    "face": null,
    "start_line_idx": 77,
    "end_line_idx": 79,
    "num_content_lines": 1
  },
  {
    "idx": 13,
    "face": null,
    "start_line_idx": 86,
    "end_line_idx": 90,
    "num_content_lines": 3
  },
  {
    "idx": 14,
    "face": null,
    "start_line_idx": 93,
    "end_line_idx": 95,
    "num_content_lines": 1
  },
  {
    "idx": 15,
    "face": null,
    "start_line_idx": 104,
    "end_line_idx": 106,
    "num_content_lines": 1
  },
  {
    "idx": 16,
    "face": null,
    "start_line_idx": 109,
    "end_line_idx": 111,
    "num_content_lines": 1
  },
  {
    "idx": 17,
    "face": null,
    "start_line_idx": 114,
    "end_line_idx": 117,
    "num_content_lines": 2
  },
  {
    "idx": 18,
    "face": null,
    "start_line_idx": 120,
    "end_line_idx": 122,
    "num_content_lines": 1
  },
  {
    "idx": 19,
    "face": null,
    "start_line_idx": 125,
    "end_line_idx": 127,
    "num_content_lines": 1
  },
  {
    "idx": 20,
    "face": null,
    "start_line_idx": 134,
    "end_line_idx": 138,
    "num_content_lines": 3
  },
  {
    "idx": 21,
    "face": null,
    "start_line_idx": 141,
    "end_line_idx": 143,
    "num_content_lines": 1
  },
  {
    "idx": 22,
    "face": null,
    "start_line_idx": 152,
    "end_line_idx": 154,
    "num_content_lines": 1
  },
  {
    "idx": 23,
    "face": null,
    "start_line_idx": 157,
    "end_line_idx": 159,
    "num_content_lines": 1
  },
  {
    "idx": 24,
    "face": null,
    "start_line_idx": 162,
    "end_line_idx": 165,
    "num_content_lines": 2
  },
  {
    "idx": 25,
    "face": null,
    "start_line_idx": 168,
    "end_line_idx": 170,
    "num_content_lines": 1
  },
  {
    "idx": 26,
    "face": null,
    "start_line_idx": 173,
    "end_line_idx": 175,
    "num_content_lines": 1
  },
  {
    "idx": 27,
    "face": null,
    "start_line_idx": 182,
    "end_line_idx": 186,
    "num_content_lines": 3
  },
  {
    "idx": 28,
    "face": null,
    "start_line_idx": 189,
    "end_line_idx": 191,
    "num_content_lines": 1
  },
  {
    "idx": 29,
    "face": null,
    "start_line_idx": 200,
    "end_line_idx": 202,
    "num_content_lines": 1
  },
  {
    "idx": 30,
    "face": null,
    "start_line_idx": 205,
    "end_line_idx": 207,
    "num_content_lines": 1
  },
  {
    "idx": 31,
    "face": null,
    "start_line_idx": 210,
    "end_line_idx": 213,
    "num_content_lines": 2
  },
  {
    "idx": 32,
    "face": null,
    "start_line_idx": 216,
    "end_line_idx": 218,
    "num_content_lines": 1
  },
  {
    "idx": 33,
    "face": null,
    "start_line_idx": 221,
    "end_line_idx": 223,
    "num_content_lines": 1
  },
  {
    "idx": 34,
    "face": null,
    "start_line_idx": 230,
    "end_line_idx": 234,
    "num_content_lines": 3
  },
  {
    "idx": 35,
    "face": null,
    "start_line_idx": 237,
    "end_line_idx": 239,
    "num_content_lines": 1
  },
  {
    "idx": 36,
    "face": null,
    "start_line_idx": 248,
    "end_line_idx": 250,
    "num_content_lines": 1
  },
  {
    "idx": 37,
    "face": null,
    "start_line_idx": 253,
    "end_line_idx": 255,
    "num_content_lines": 1
  },
  {
    "idx": 38,
    "face": null,
    "start_line_idx": 258,
    "end_line_idx": 261,
    "num_content_lines": 2
  },
  {
    "idx": 39,
    "face": null,
    "start_line_idx": 264,
    "end_line_idx": 266,
    "num_content_lines": 1
  },
  {
    "idx": 40,
    "face": null,
    "start_line_idx": 269,
    "end_line_idx": 271,
    "num_content_lines": 1
  },
  {
    "idx": 41,
    "face": null,
    "start_line_idx": 278,
    "end_line_idx": 282,
    "num_content_lines": 3
  },
  {
    "idx": 42,
    "face": null,
    "start_line_idx": 285,
    "end_line_idx": 287,
    "num_content_lines": 1
  },
  {
    "idx": 43,
    "face": null,
    "start_line_idx": 296,
    "end_line_idx": 298,
    "num_content_lines": 1
  },
  {
    "idx": 44,
    "face": null,
    "start_line_idx": 301,
    "end_line_idx": 303,
    "num_content_lines": 1
  },
  {
    "idx": 45,
    "face": null,
    "start_line_idx": 306,
    "end_line_idx": 309,
    "num_content_lines": 2
  },
  {
    "idx": 46,
    "face": null,
    "start_line_idx": 312,
    "end_line_idx": 314,
    "num_content_lines": 1
  },
  {
    "idx": 47,
    "face": null,
    "start_line_idx": 317,
    "end_line_idx": 319,
    "num_content_lines": 1
  },
  {
    "idx": 48,
    "face": null,
    "start_line_idx": 326,
    "end_line_idx": 330,
    "num_content_lines": 3
  },
  {
    "idx": 49,
    "face": null,
    "start_line_idx": 333,
    "end_line_idx": 335,
    "num_content_lines": 1
  },
  {
    "idx": 50,
    "face": null,
    "start_line_idx": 344,
    "end_line_idx": 346,
    "num_content_lines": 1
  },
  {
    "idx": 51,
    "face": null,
    "start_line_idx": 349,
    "end_line_idx": 351,
    "num_content_lines": 1
  },
  {
    "idx": 52,
    "face": null,
    "start_line_idx": 354,
    "end_line_idx": 357,
    "num_content_lines": 2
  },
  {
    "idx": 53,
    "face": null,
    "start_line_idx": 360,
    "end_line_idx": 362,
    "num_content_lines": 1
  },
  {
    "idx": 54,
    "face": null,
    "start_line_idx": 365,
    "end_line_idx": 367,
    "num_content_lines": 1
  },
  {
    "idx": 55,
    "face": null,
    "start_line_idx": 374,
    "end_line_idx": 376,
    "num_content_lines": 1
  }
]